odoo10_addon_hr_employee_legacy_id-10.0.1.0.0.99.dev9-py2.7-nspkg.pth
odoo/addons/hr_employee_legacy_id/README.rst
odoo/addons/hr_employee_legacy_id/__init__.py
odoo/addons/hr_employee_legacy_id/__manifest__.py
odoo/addons/hr_employee_legacy_id/i18n/ar.po
odoo/addons/hr_employee_legacy_id/i18n/cs_CZ.po
odoo/addons/hr_employee_legacy_id/i18n/de.po
odoo/addons/hr_employee_legacy_id/i18n/es.po
odoo/addons/hr_employee_legacy_id/i18n/fi.po
odoo/addons/hr_employee_legacy_id/i18n/fr.po
odoo/addons/hr_employee_legacy_id/i18n/hr.po
odoo/addons/hr_employee_legacy_id/i18n/hr_HR.po
odoo/addons/hr_employee_legacy_id/i18n/hr_employee_legacy_id.pot
odoo/addons/hr_employee_legacy_id/i18n/it.po
odoo/addons/hr_employee_legacy_id/i18n/lt.po
odoo/addons/hr_employee_legacy_id/i18n/nl_NL.po
odoo/addons/hr_employee_legacy_id/i18n/pt_BR.po
odoo/addons/hr_employee_legacy_id/i18n/ro.po
odoo/addons/hr_employee_legacy_id/i18n/sl.po
odoo/addons/hr_employee_legacy_id/models/__init__.py
odoo/addons/hr_employee_legacy_id/models/hr.py
odoo/addons/hr_employee_legacy_id/static/description/icon.png
odoo/addons/hr_employee_legacy_id/views/hr_view.xml
odoo10_addon_hr_employee_legacy_id-10.0.1.0.0.99.dev9.dist-info/METADATA
odoo10_addon_hr_employee_legacy_id-10.0.1.0.0.99.dev9.dist-info/RECORD
odoo10_addon_hr_employee_legacy_id-10.0.1.0.0.99.dev9.dist-info/WHEEL
odoo10_addon_hr_employee_legacy_id-10.0.1.0.0.99.dev9.dist-info/namespace_packages.txt
odoo10_addon_hr_employee_legacy_id-10.0.1.0.0.99.dev9.dist-info/top_level.txt
